slack_bundle/__init__.py
slack_bundle/bundle.py
slack_bundle-1.1.dist-info/DESCRIPTION.rst
slack_bundle-1.1.dist-info/METADATA
slack_bundle-1.1.dist-info/RECORD
slack_bundle-1.1.dist-info/WHEEL
slack_bundle-1.1.dist-info/metadata.json
slack_bundle-1.1.dist-info/top_level.txt
